async_hcaptcha/__init__.py
async_hcaptcha/asynchcaptcha.py
async_hcaptcha/utils.py
async_hcaptcha/window.js
async_hcaptcha-1.0.0b11.dist-info/LICENSE
async_hcaptcha-1.0.0b11.dist-info/METADATA
async_hcaptcha-1.0.0b11.dist-info/WHEEL
async_hcaptcha-1.0.0b11.dist-info/top_level.txt
async_hcaptcha-1.0.0b11.dist-info/RECORD
