Metadata-Version: 2.1
Name: async-hcaptcha
Version: 1.0.0b11
Summary: Unofficial async wrapper for interacting with hCaptcha
Home-page: https://github.com/RuslanUC/aio-hcaptcha
Author: RuslanUC
License: MIT
Classifier: Operating System :: OS Independent
Classifier: Programming Language :: Python :: 3.7
Classifier: Programming Language :: Python :: 3.8
Classifier: Programming Language :: Python :: 3.9
Classifier: Programming Language :: Python :: 3.10
Classifier: Topic :: Internet
Classifier: Topic :: Software Development :: Libraries
Classifier: Topic :: Software Development :: Libraries :: Python Modules
Classifier: Topic :: Utilities
Requires-Python: >=3.7
License-File: LICENSE
Requires-Dist: aiohttp (~=3.8.1)
Requires-Dist: selenium (~=4.1.5)
Requires-Dist: hcaptcha-challenger
